dexcolor/__init__.py
dexcolor/background.py
dexcolor/dex.py
dexcolor/rt.py
dexcolor/styles.py
dexcolor-1.0.dist-info/LICENSE
dexcolor-1.0.dist-info/METADATA
dexcolor-1.0.dist-info/WHEEL
dexcolor-1.0.dist-info/top_level.txt
dexcolor-1.0.dist-info/RECORD
