Metadata-Version: 2.1
Name: dexcolor
Version: 1.0
Summary: Terminal colored text.
Author-email: Terong333 <thisterong33@proton.me>
Project-URL: Homepage, https://github.com/Terong33/dexcolor
Project-URL: PyPI_page, https://pypi.org/project/dexcolor/
Classifier: Programming Language :: Python
Classifier: Programming Language :: Python :: 3
Classifier: License :: OSI Approved :: MIT License
Classifier: Operating System :: OS Independent
Classifier: Topic :: Terminals
Requires-Python: >=3.7
License-File: LICENSE
